gridijkstra/__init__.py
gridijkstra/_version.py
gridijkstra/routing.py
gridikjstra-0.1.dist-info/DESCRIPTION.rst
gridikjstra-0.1.dist-info/METADATA
gridikjstra-0.1.dist-info/RECORD
gridikjstra-0.1.dist-info/WHEEL
gridikjstra-0.1.dist-info/metadata.json
gridikjstra-0.1.dist-info/top_level.txt
