Metadata-Version: 2.0
Name: gridikjstra
Version: 0.1
Summary: Python package wrapping scipy's dijkstra with a grid-based interface
Home-page: UNKNOWN
Author: Vegard Kvernelv
License: UNKNOWN
Platform: UNKNOWN
Classifier: Programming Language :: Python :: 3
Classifier: License :: OSI Approved :: MIT License
Classifier: Operating System :: OS Independent
Requires-Python: >=3.6
